[{"password":"cGFzczE=","games":[{"price":150,"name":"Assassin's Creed"},{"price":100,"name":"Watch Dogs"}],"credit":"750","username":"id1"},{"password":"cGFzczI=","games":[{"price":250,"name":"FIFA 20"},{"price":25,"name":"Poker"}],"credit":"725","username":"id2"},{"password":"cGFzczM=","games":[{"price":150,"name":"Assassin's Creed"},{"price":25,"name":"CS:GO"},{"price":25,"name":"Poker"},{"price":100,"name":"Watch Dogs"},{"price":200,"name":"NFS Heat"},{"price":250,"name":"FIFA 20"}],"credit":"250","username":"id3"},{"password":"cGFzczQ=","games":[],"credit":"1000","username":"id4"},{"password":"cGFzczU=","games":[{"price":200,"name":"NFS Heat"},{"price":250,"name":"FIFA 20"},{"price":100,"name":"Watch Dogs"},{"price":25,"name":"Poker"},{"price":25,"name":"CS:GO"},{"price":150,"name":"Assassin's Creed"}],"credit":"25","username":"id5"},{"password":"cGFzczY=","games":[{"price":200,"name":"NFS Heat"},{"price":100,"name":"Watch Dogs"},{"price":250,"name":"FIFA 20"},{"price":150,"name":"Assassin's Creed"},{"price":25,"name":"Poker"},{"price":25,"name":"CS:GO"}],"credit":"50","username":"id6"},{"password":"cGFzczc=","games":[{"price":150,"name":"Assassin's Creed"},{"price":250,"name":"FIFA 20"},{"price":100,"name":"Watch Dogs"}],"credit":"0","username":"id7"},{"password":"cGFzczg=","games":[],"credit":"1000","username":"id8"},{"password":"cGFzczk=","games":[],"credit":"1000","username":"id9"},{"password":"cGFzczEw","games":[{"price":150,"name":"Assassin's Creed"}],"credit":"850","username":"id10"}]